{
  "access": [
    "Everybody"
  ],
  "components": [
    {
      "components": [
        {
          "name": "pageTitle",
          "size": "H1",
          "style": {
            "display": "inline",
            "float": "none"
          },
          "text": "TextArea",
          "type": "heading"
        },
        {
          "icon": "",
          "name": "link0",
          "path": "https://github.com/akorchev/angular.radzen.com/blob/master/meta/pages/text-area.json",
          "text": "[source code]",
          "type": "link"
        },
        {
          "name": "heading0",
          "size": "H4",
          "text": "This page demonstrates TextArea component.",
          "type": "heading"
        },
        {
          "components": [
            {
              "components": [
                {
                  "class": "col-md-6",
                  "components": [
                    {
                      "name": "heading2",
                      "size": "H3",
                      "text": "TextArea with 100 max chars",
                      "type": "heading"
                    },
                    {
                      "cols": 40,
                      "events": {
                        "change": [
                          {
                            "code": "${events.unshift('TextArea Change: ' + JSON.stringify(event))}",
                            "type": "execute"
                          }
                        ]
                      },
                      "maxLength": 100,
                      "name": "textarea0",
                      "placeholder": "Enter text ...",
                      "rows": 5,
                      "type": "textarea",
                      "value": ""
                    }
                  ],
                  "name": "col0",
                  "type": "col"
                },
                {
                  "class": "col-md-6",
                  "components": [
                    {
                      "name": "heading1",
                      "size": "H3",
                      "text": "Events",
                      "type": "heading"
                    },
                    {
                      "components": [
                        {
                          "content": "<div style=\"overflow:auto;height:100%\">\n  <div *ngFor=\"let event of events\">\n      {{ event }}\n  </div>\n</div>\n",
                          "name": "html0",
                          "type": "html"
                        }
                      ],
                      "name": "card1",
                      "style": {
                        "height": "500px"
                      },
                      "type": "card",
                      "visible": true
                    }
                  ],
                  "name": "col1",
                  "type": "col"
                }
              ],
              "name": "row0",
              "type": "row"
            }
          ],
          "name": "card0",
          "style": {
            "height": "600px"
          },
          "type": "card",
          "visible": true
        }
      ],
      "container": "main",
      "type": "content"
    }
  ],
  "events": {
    "load": [
      {
        "name": "events",
        "type": "set",
        "value": "[]"
      }
    ]
  },
  "layout": "Main",
  "name": "TextArea"
}